license_analyzer/__init__.py
license_analyzer/cli.py
license_analyzer/core.py
license_analyzer/updater.py
license_analyzer-0.0.4.dist-info/licenses/LICENSE
license_analyzer-0.0.4.dist-info/METADATA
license_analyzer-0.0.4.dist-info/WHEEL
license_analyzer-0.0.4.dist-info/entry_points.txt
license_analyzer-0.0.4.dist-info/top_level.txt
license_analyzer-0.0.4.dist-info/RECORD
