Metadata-Version: 2.4
Name: license-analyzer
Version: 0.0.4
Summary: A robust Python module for analyzing and comparing software licenses
Author-email: envolution <involution@gmail.com>
Project-URL: Homepage, https://github.com/envolution/license-analyzer
Project-URL: Bug Tracker, https://github.com/envolution/license-analyzer/issues
Classifier: Development Status :: 4 - Beta
Classifier: Intended Audience :: Developers
Classifier: License :: OSI Approved :: MIT License
Classifier: Operating System :: OS Independent
Classifier: Programming Language :: Python :: 3
Classifier: Programming Language :: Python :: 3.8
Classifier: Programming Language :: Python :: 3.9
Classifier: Programming Language :: Python :: 3.10
Classifier: Programming Language :: Python :: 3.11
Classifier: Programming Language :: Python :: 3.12
Classifier: Programming Language :: Python :: 3.13
Classifier: Topic :: Software Development :: Libraries :: Python Modules
Classifier: Topic :: Utilities
Requires-Python: >=3.8
License-File: LICENSE
Requires-Dist: numpy>=1.21.0
Requires-Dist: sentence-transformers>=2.0.0
Requires-Dist: torch>=1.9.0
Requires-Dist: transformers>=4.0.0
Requires-Dist: requests>=2.0.0
Requires-Dist: appdirs>=1.4.4
Requires-Dist: rich>=12.0.0
Provides-Extra: dev
Requires-Dist: pytest>=6.0; extra == "dev"
Requires-Dist: pytest-cov>=2.0; extra == "dev"
Requires-Dist: black>=21.0; extra == "dev"
Requires-Dist: flake8>=3.8; extra == "dev"
Requires-Dist: mypy>=0.800; extra == "dev"
Requires-Dist: sphinx>=4.0; extra == "dev"
Requires-Dist: sphinx-rtd-theme>=1.0; extra == "dev"
Dynamic: license-file
